[
  {
    "chain_slug": "solana",
    "chain_id": 501474,
    "address": "So11111111111111111111111111111111111111112",
    "symbol": "SOL",
    "name": "Wrapped SOL",
    "market_cap_usd": 49162269054,
    "volume_24h_usd": 167842387,
    "liquidity_usd": 25436049,
    "logo_uri": "https://cdn.dexscreener.com/cms/images/fcfb87378d3198fe753ca08ba51a5552a84f34cf48cd09d83971aa195bdf00d2?width=800&height=800&quality=95&format=auto",
    "pair_created_at_ms": 1669602308000,
    "dexscreener_url": "https://dexscreener.com/solana/So11111111111111111111111111111111111111112",
    "decimals": 9
  },
  {
    "chain_slug": "base",
    "chain_id": 8453,
    "address": "0x4200000000000000000000000000000000000006",
    "symbol": "WETH",
    "name": "Wrapped Ether",
    "market_cap_usd": 493890485,
    "volume_24h_usd": 103003278,
    "liquidity_usd": 8943529,
    "logo_uri": "https://cdn.dexscreener.com/cms/images/e7ad3f643e8706e541538413f2afad46f18cafb430606caae3c70c0f7425c16e?width=800&height=800&quality=95&format=auto",
    "pair_created_at_ms": 1691013975000,
    "dexscreener_url": "https://dexscreener.com/base/0x4200000000000000000000000000000000000006",
    "decimals": 18
  },
  {
    "chain_slug": "base",
    "chain_id": 8453,
    "address": "0xcbb7c0000ab88b473b1f5afd9ef808440eed33bf",
    "symbol": "cbBTC",
    "name": "Coinbase Wrapped BTC",
    "market_cap_usd": 2683092919,
    "volume_24h_usd": 89693959,
    "liquidity_usd": 8850134,
    "logo_uri": "https://cdn.dexscreener.com/cms/images/07ce833f9dde758de45cb2476e630226f9b58418bb20e0f7ce3885c5d0d80b1b?width=800&height=800&quality=95&format=auto",
    "pair_created_at_ms": 1726084175000,
    "dexscreener_url": "https://dexscreener.com/base/0xcbb7c0000ab88b473b1f5afd9ef808440eed33bf",
    "decimals": 8
  },
  {
    "chain_slug": "solana",
    "chain_id": 501474,
    "address": "9cRCn9rGT8V2imeM2BaKs13yhMEais3ruM3rPvTGpump",
    "symbol": "ANSEM",
    "name": "The Black Bull",
    "market_cap_usd": 314685012,
    "volume_24h_usd": 42192383,
    "liquidity_usd": 2828779,
    "logo_uri": "https://cdn.dexscreener.com/cms/images/A8aHRXC8VPrpfPIF?width=800&height=800&quality=95&format=auto",
    "pair_created_at_ms": 1781643948000,
    "dexscreener_url": "https://dexscreener.com/solana/9cRCn9rGT8V2imeM2BaKs13yhMEais3ruM3rPvTGpump",
    "decimals": 6
  },
  {
    "chain_slug": "solana",
    "chain_id": 501474,
    "address": "6NwarBvDkXhByqVp2Qkq5i9XbtA2B3Bwe8SWGu9vpump",
    "symbol": "Cupsey",
    "name": "Cupsey",
    "market_cap_usd": 9732828,
    "volume_24h_usd": 9417535,
    "liquidity_usd": 277861,
    "logo_uri": "https://cdn.dexscreener.com/cms/images/2f15881989e154700fcf266cb7b46441cec568f68d60009051ee0c97514d147b?width=800&height=800&quality=95&format=auto",
    "dexscreener_url": "https://dexscreener.com/solana/6NwarBvDkXhByqVp2Qkq5i9XbtA2B3Bwe8SWGu9vpump",
    "decimals": 6
  },
  {
    "chain_slug": "solana",
    "chain_id": 501474,
    "address": "HQJdVyNpAFSwJzeJTuR8Go2YmvtkmhyZD6X3xeyJpump",
    "symbol": "RETIRE",
    "name": "LOCK IN AND RETIRE",
    "market_cap_usd": 54115465,
    "volume_24h_usd": 8909627,
    "liquidity_usd": 3076377,
    "logo_uri": "https://cdn.dexscreener.com/cms/images/IcIXZa_vDl-pL9wZ?width=800&height=800&quality=95&format=auto",
    "dexscreener_url": "https://dexscreener.com/solana/HQJdVyNpAFSwJzeJTuR8Go2YmvtkmhyZD6X3xeyJpump",
    "decimals": 6
  },
  {
    "chain_slug": "solana",
    "chain_id": 501474,
    "address": "E2ueKQ3EDTTmCkUA17j3KeTb2u6VT91xiyECdKRzpump",
    "symbol": "tolywifhat",
    "name": "baby toly wif hat",
    "market_cap_usd": 3214976,
    "volume_24h_usd": 5292635,
    "liquidity_usd": 171577,
    "logo_uri": "https://cdn.dexscreener.com/cms/images/OpJPWh_yKAlsKzfm?width=800&height=800&quality=95&format=auto",
    "dexscreener_url": "https://dexscreener.com/solana/E2ueKQ3EDTTmCkUA17j3KeTb2u6VT91xiyECdKRzpump",
    "decimals": 6
  },
  {
    "chain_slug": "solana",
    "chain_id": 501474,
    "address": "6xCtR2Eq1VumsoRdNutcfSQfLMk7xUa2BrMx18tqpump",
    "symbol": "DEXBULL",
    "name": "The Dextools Bull",
    "market_cap_usd": 2636316,
    "volume_24h_usd": 5243917,
    "liquidity_usd": 128462,
    "logo_uri": "https://cdn.dexscreener.com/cms/images/PeBSlBXPUaMa0_DA?width=800&height=800&quality=95&format=auto",
    "dexscreener_url": "https://dexscreener.com/solana/6xCtR2Eq1VumsoRdNutcfSQfLMk7xUa2BrMx18tqpump",
    "decimals": 6
  },
  {
    "chain_slug": "solana",
    "chain_id": 501474,
    "address": "Es9vMFrzaCERmJfrF4H2FYD4KCoNkY11McCe8BenwNYB",
    "symbol": "USDT",
    "name": "USDT",
    "market_cap_usd": 225249509204,
    "volume_24h_usd": 4855901,
    "liquidity_usd": 15382138,
    "logo_uri": "https://cdn.dexscreener.com/cms/images/ad986e3ebe668b0c5ed2ecec0f6bcdc2f4cda3ad8a424a252d33f730c75364a7?width=800&height=800&quality=95&format=auto",
    "pair_created_at_ms": 1669602314000,
    "dexscreener_url": "https://dexscreener.com/solana/Es9vMFrzaCERmJfrF4H2FYD4KCoNkY11McCe8BenwNYB",
    "decimals": 6
  },
  {
    "chain_slug": "solana",
    "chain_id": 501474,
    "address": "7aD86TAvoXPBAkt7HxGsz3MG8UBdDUvcVeBLouVcpump",
    "symbol": "BULLSEY",
    "name": "Bull Cupsey",
    "market_cap_usd": 1664866,
    "volume_24h_usd": 4533459,
    "liquidity_usd": 6663,
    "logo_uri": "https://cdn.dexscreener.com/cms/images/sYVIsnodMfk3qDeX?width=800&height=800&quality=95&format=auto",
    "dexscreener_url": "https://dexscreener.com/solana/7aD86TAvoXPBAkt7HxGsz3MG8UBdDUvcVeBLouVcpump",
    "decimals": 6
  },
  {
    "chain_slug": "solana",
    "chain_id": 501474,
    "address": "4eKYoR1hBHnRaYyg2d57H36uUatRNyZr1NRP9ScNpump",
    "symbol": "DONALT",
    "name": "The Duck Bull",
    "market_cap_usd": 4063878,
    "volume_24h_usd": 4341865,
    "liquidity_usd": 190773,
    "logo_uri": "https://cdn.dexscreener.com/cms/images/9DzCI49c9rvL_sPo?width=800&height=800&quality=95&format=auto",
    "dexscreener_url": "https://dexscreener.com/solana/4eKYoR1hBHnRaYyg2d57H36uUatRNyZr1NRP9ScNpump",
    "decimals": 6
  },
  {
    "chain_slug": "base",
    "chain_id": 8453,
    "address": "0x940181a94a35a4569e4529a3cdfb74e38fd98631",
    "symbol": "AERO",
    "name": "Aerodrome",
    "market_cap_usd": 515541526,
    "volume_24h_usd": 3902824,
    "liquidity_usd": 31687137,
    "logo_uri": "https://cdn.dexscreener.com/cms/images/f950c4e0a9ded4f6b5c811cf33570a65c6f7ea8630d937cd69065269e9dc3a03?width=800&height=800&quality=95&format=auto",
    "pair_created_at_ms": 1694127045000,
    "dexscreener_url": "https://dexscreener.com/base/0x940181a94a35a4569e4529a3cdfb74e38fd98631",
    "decimals": 18
  },
  {
    "chain_slug": "base",
    "chain_id": 8453,
    "address": "0x0b3e328455c4059eeb9e3f84b5543f74e24e7e1b",
    "symbol": "VIRTUAL",
    "name": "Virtual Protocol",
    "market_cap_usd": 346161734,
    "volume_24h_usd": 3744125,
    "liquidity_usd": 586316,
    "logo_uri": "https://cdn.dexscreener.com/cms/images/461f4a6b70979b82b7141adc522389c67043535a082d65accebf49013c798386?width=800&height=800&quality=95&format=auto",
    "pair_created_at_ms": 1710514799000,
    "dexscreener_url": "https://dexscreener.com/base/0x0b3e328455c4059eeb9e3f84b5543f74e24e7e1b",
    "decimals": 18
  },
  {
    "chain_slug": "base",
    "chain_id": 8453,
    "address": "0x311935cd80b76769bf2ecc9d8ab7635b2139cf82",
    "symbol": "SOL",
    "name": "Solana",
    "market_cap_usd": 14814396,
    "volume_24h_usd": 3706640,
    "liquidity_usd": 385616,
    "logo_uri": "https://cdn.dexscreener.com/cms/images/e06bde6f35af4295de2c1b039f242b464012689ad6fc669ee977a9148b2eb936?width=800&height=800&quality=95&format=auto",
    "pair_created_at_ms": 1764722545000,
    "dexscreener_url": "https://dexscreener.com/base/0x311935cd80b76769bf2ecc9d8ab7635b2139cf82",
    "decimals": 9
  },
  {
    "chain_slug": "solana",
    "chain_id": 501474,
    "address": "22deNCri9bBae1GWZxdaDxipMWdwAUQ2ddvxdSmgpump",
    "symbol": "CASHCAT",
    "name": "Cash Cat",
    "market_cap_usd": 405331,
    "volume_24h_usd": 3564367,
    "liquidity_usd": 57645,
    "logo_uri": "https://cdn.dexscreener.com/cms/images/l2Bolk0D73ojFCEX?width=800&height=800&quality=95&format=auto",
    "dexscreener_url": "https://dexscreener.com/solana/22deNCri9bBae1GWZxdaDxipMWdwAUQ2ddvxdSmgpump",
    "decimals": 6
  },
  {
    "chain_slug": "solana",
    "chain_id": 501474,
    "address": "4gqUH4qMtkZTjeenrtVmcQXKEYg9aBUC8j2kQao2pump",
    "symbol": "MASON",
    "name": "MASON VERSLUIS",
    "market_cap_usd": 427398,
    "volume_24h_usd": 2861250,
    "liquidity_usd": 25599,
    "logo_uri": "https://cdn.dexscreener.com/cms/images/9sS3PNgkCBl5xoyU?width=800&height=800&quality=95&format=auto",
    "dexscreener_url": "https://dexscreener.com/solana/4gqUH4qMtkZTjeenrtVmcQXKEYg9aBUC8j2kQao2pump",
    "decimals": 6
  },
  {
    "chain_slug": "solana",
    "chain_id": 501474,
    "address": "DdPrHYqM8Ueovnk9kAnAgoGhswkuaTqmxcoZzU3Zpump",
    "symbol": "manlet",
    "name": "manlet",
    "market_cap_usd": 4433399,
    "volume_24h_usd": 2440524,
    "liquidity_usd": 225495,
    "logo_uri": "https://cdn.dexscreener.com/cms/images/xnH8mWLYKU8ZWLD_?width=800&height=800&quality=95&format=auto",
    "pair_created_at_ms": 1782772288000,
    "dexscreener_url": "https://dexscreener.com/solana/DdPrHYqM8Ueovnk9kAnAgoGhswkuaTqmxcoZzU3Zpump",
    "decimals": 6
  },
  {
    "chain_slug": "solana",
    "chain_id": 501474,
    "address": "CizcDa22HJjXybKLriibqP167GcJjqiDHDPtuiMmpump",
    "symbol": "ok",
    "name": "ok",
    "market_cap_usd": 1066713,
    "volume_24h_usd": 2275531,
    "liquidity_usd": 90622,
    "logo_uri": "https://cdn.dexscreener.com/cms/images/JwTiYesc92LUUhSa?width=800&height=800&quality=95&format=auto",
    "dexscreener_url": "https://dexscreener.com/solana/CizcDa22HJjXybKLriibqP167GcJjqiDHDPtuiMmpump",
    "decimals": 6
  },
  {
    "chain_slug": "base",
    "chain_id": 8453,
    "address": "0xacfe6019ed1a7dc6f7b508c02d1b04ec88cc21bf",
    "symbol": "VVV",
    "name": "Venice Token",
    "market_cap_usd": 539098400,
    "volume_24h_usd": 2094425,
    "liquidity_usd": 2062957,
    "logo_uri": "https://cdn.dexscreener.com/cms/images/a581d4cf10079a278196c97485dda06cf4fb77d539a94f8d986be6d1f2445ddc?width=800&height=800&quality=95&format=auto",
    "pair_created_at_ms": 1737996283000,
    "dexscreener_url": "https://dexscreener.com/base/0xacfe6019ed1a7dc6f7b508c02d1b04ec88cc21bf",
    "decimals": 18
  },
  {
    "chain_slug": "base",
    "chain_id": 8453,
    "address": "0x9c5c365e764829876243d0b289733b9d2b729685",
    "symbol": "deSPXA",
    "name": "SPXA deRWA",
    "market_cap_usd": 3178987,
    "volume_24h_usd": 1975598,
    "liquidity_usd": 3081298,
    "logo_uri": "https://cdn.dexscreener.com/cms/images/lR_7ABSP-Vyw9_55?width=800&height=800&quality=95&format=auto",
    "pair_created_at_ms": 1777889361000,
    "dexscreener_url": "https://dexscreener.com/base/0x9c5c365e764829876243d0b289733b9d2b729685",
    "decimals": 18
  },
  {
    "chain_slug": "base",
    "chain_id": 8453,
    "address": "0xbf927b841994731c573bdf09ceb0c6b0aa887cdd",
    "symbol": "VELVET",
    "name": "Velvet",
    "market_cap_usd": 168712065,
    "volume_24h_usd": 1851069,
    "liquidity_usd": 2974200,
    "logo_uri": "https://cdn.dexscreener.com/cms/images/922f6888648f06e8a6e228aef05660cc68814596d9921d33efea723cf16b77ff?width=800&height=800&quality=95&format=auto",
    "pair_created_at_ms": 1757351299000,
    "dexscreener_url": "https://dexscreener.com/base/0xbf927b841994731c573bdf09ceb0c6b0aa887cdd",
    "decimals": 18
  },
  {
    "chain_slug": "solana",
    "chain_id": 501474,
    "address": "FMqh9mqR6drPZqqW6wPqLHxX4rqNDWGhYLaMfoaJpump",
    "symbol": "world",
    "name": "world.xyz",
    "market_cap_usd": 2746588,
    "volume_24h_usd": 1778554,
    "liquidity_usd": 193065,
    "logo_uri": "https://cdn.dexscreener.com/cms/images/xJc5jA3Ech8TdeZ2?width=800&height=800&quality=95&format=auto",
    "pair_created_at_ms": 1782226393000,
    "dexscreener_url": "https://dexscreener.com/solana/FMqh9mqR6drPZqqW6wPqLHxX4rqNDWGhYLaMfoaJpump",
    "decimals": 6
  },
  {
    "chain_slug": "solana",
    "chain_id": 501474,
    "address": "h5NciPdMZ5QCB5BYETJMYBMpVx9ZuitR6HcVjyBhood",
    "symbol": "HOOD",
    "name": "Robinhood",
    "market_cap_usd": 39419019,
    "volume_24h_usd": 1611045,
    "liquidity_usd": 227577,
    "logo_uri": "https://cdn.dexscreener.com/cms/images/bb806743d29a5b76012b7a3b634f33e08117e9876c1d216ef1d5fa2f34303975?width=800&height=800&quality=95&format=auto",
    "dexscreener_url": "https://dexscreener.com/solana/h5NciPdMZ5QCB5BYETJMYBMpVx9ZuitR6HcVjyBhood",
    "decimals": 6
  },
  {
    "chain_slug": "solana",
    "chain_id": 501474,
    "address": "6baGyq4HLbUn93MQUGFqBktpXP8BRjpoxSsAap4ppump",
    "symbol": "LEVI",
    "name": "The White Bull",
    "market_cap_usd": 2008911,
    "volume_24h_usd": 1557603,
    "liquidity_usd": 134695,
    "logo_uri": "https://cdn.dexscreener.com/cms/images/VwxqlbgO3QZ2CG6f?width=800&height=800&quality=95&format=auto",
    "dexscreener_url": "https://dexscreener.com/solana/6baGyq4HLbUn93MQUGFqBktpXP8BRjpoxSsAap4ppump",
    "decimals": 6
  },
  {
    "chain_slug": "solana",
    "chain_id": 501474,
    "address": "CFPkPq1eYPR8GLzEo59wUbbMioX4bshaTQiSGzTSpump",
    "symbol": "MENSA",
    "name": "The Black Table",
    "market_cap_usd": 2873686,
    "volume_24h_usd": 1269331,
    "liquidity_usd": 166189,
    "logo_uri": "https://cdn.dexscreener.com/cms/images/opELNR-Yxm77hCIY?width=800&height=800&quality=95&format=auto",
    "dexscreener_url": "https://dexscreener.com/solana/CFPkPq1eYPR8GLzEo59wUbbMioX4bshaTQiSGzTSpump",
    "decimals": 6
  },
  {
    "chain_slug": "base",
    "chain_id": 8453,
    "address": "0xcb111e6a2a3bde90856d299d61341ac302167d23",
    "symbol": "cbMEGA",
    "name": "Coinbase Wrapped MEGA",
    "market_cap_usd": 1526044,
    "volume_24h_usd": 1200456,
    "liquidity_usd": 278273,
    "logo_uri": "https://cdn.dexscreener.com/cms/images/4_yrDLCS1IXefTvi?width=800&height=800&quality=95&format=auto",
    "pair_created_at_ms": 1777562779000,
    "dexscreener_url": "https://dexscreener.com/base/0xcb111e6a2a3bde90856d299d61341ac302167d23",
    "decimals": 18
  },
  {
    "chain_slug": "solana",
    "chain_id": 501474,
    "address": "6AJcP7wuLwmRYLBNbi825wgguaPsWzPBEHcHndpRpump",
    "symbol": "VINE",
    "name": "Vine Coin",
    "market_cap_usd": 176741401,
    "volume_24h_usd": 1055249,
    "liquidity_usd": 1434577,
    "logo_uri": "https://cdn.dexscreener.com/cms/images/74a2255eb11fd430603a2ae1823456c98a5e241fa2e526c253c92ad16d1fa1ce?width=800&height=800&quality=95&format=auto",
    "dexscreener_url": "https://dexscreener.com/solana/6AJcP7wuLwmRYLBNbi825wgguaPsWzPBEHcHndpRpump",
    "decimals": 6
  },
  {
    "chain_slug": "solana",
    "chain_id": 501474,
    "address": "5pYB12kEhfhSFXJjZ7JtyqDpt6uUqhsF6iu6Ee9spump",
    "symbol": "CATWIF",
    "name": "catwifhat",
    "market_cap_usd": 1859544,
    "volume_24h_usd": 1024985,
    "liquidity_usd": 211722,
    "logo_uri": "https://cdn.dexscreener.com/cms/images/0vDhiGlBbyJh8u8s?width=800&height=800&quality=95&format=auto",
    "pair_created_at_ms": 1782111621000,
    "dexscreener_url": "https://dexscreener.com/solana/5pYB12kEhfhSFXJjZ7JtyqDpt6uUqhsF6iu6Ee9spump",
    "decimals": 6
  },
  {
    "chain_slug": "solana",
    "chain_id": 501474,
    "address": "6AJcP7wuLwmRYLBNbi825wgguaPsWzPBEHcHndpRpump",
    "symbol": "VINE",
    "name": "Vine Coin",
    "market_cap_usd": 176741401,
    "volume_24h_usd": 1031103,
    "liquidity_usd": 1458366,
    "logo_uri": "https://cdn.dexscreener.com/cms/images/74a2255eb11fd430603a2ae1823456c98a5e241fa2e526c253c92ad16d1fa1ce?width=800&height=800&quality=95&format=auto",
    "dexscreener_url": "https://dexscreener.com/solana/6AJcP7wuLwmRYLBNbi825wgguaPsWzPBEHcHndpRpump",
    "decimals": 6
  },
  {
    "chain_slug": "solana",
    "chain_id": 501474,
    "address": "8B3UJbbPWfg2DLF7iWzm9WnXH9y5jhYUUoZaLhqvpump",
    "symbol": "ANSEMWIFE",
    "name": "The Black Queen",
    "market_cap_usd": 602253,
    "volume_24h_usd": 902414,
    "liquidity_usd": 48558,
    "logo_uri": "https://cdn.dexscreener.com/cms/images/PtYaZaY17afa77PZ?width=800&height=800&quality=95&format=auto",
    "dexscreener_url": "https://dexscreener.com/solana/8B3UJbbPWfg2DLF7iWzm9WnXH9y5jhYUUoZaLhqvpump",
    "decimals": 6
  },
  {
    "chain_slug": "solana",
    "chain_id": 501474,
    "address": "62YE1d4sRArBQzR5bdbxsx2k9LV3MdPV4xMC4Di2pump",
    "symbol": "BIF",
    "name": "bullwifhat",
    "market_cap_usd": 2006401,
    "volume_24h_usd": 776999,
    "liquidity_usd": 124043,
    "logo_uri": "https://cdn.dexscreener.com/cms/images/MtTKP4JlU6foabKT?width=800&height=800&quality=95&format=auto",
    "dexscreener_url": "https://dexscreener.com/solana/62YE1d4sRArBQzR5bdbxsx2k9LV3MdPV4xMC4Di2pump",
    "decimals": 6
  },
  {
    "chain_slug": "solana",
    "chain_id": 501474,
    "address": "2vvw3cSwibzGD6SgW9QzRaBdmjkYrvs218DUy6VWpump",
    "symbol": "SUNUSI",
    "name": "The African Bull",
    "market_cap_usd": 1273140,
    "volume_24h_usd": 632266,
    "liquidity_usd": 94125,
    "logo_uri": "https://cdn.dexscreener.com/cms/images/40MdKY7Udg7kVEZ4?width=800&height=800&quality=95&format=auto",
    "dexscreener_url": "https://dexscreener.com/solana/2vvw3cSwibzGD6SgW9QzRaBdmjkYrvs218DUy6VWpump",
    "decimals": 6
  },
  {
    "chain_slug": "solana",
    "chain_id": 501474,
    "address": "DLvuaz18bKnh1hEaCZsZ5NgJi7wYFm5RvgZVA2M5pump",
    "symbol": "BABYANSEM",
    "name": "The Black Calf",
    "market_cap_usd": 851603,
    "volume_24h_usd": 423511,
    "liquidity_usd": 96022,
    "logo_uri": "https://cdn.dexscreener.com/cms/images/KqRgAp8qG6FIHVwv?width=800&height=800&quality=95&format=auto",
    "dexscreener_url": "https://dexscreener.com/solana/DLvuaz18bKnh1hEaCZsZ5NgJi7wYFm5RvgZVA2M5pump",
    "decimals": 6
  },
  {
    "chain_slug": "solana",
    "chain_id": 501474,
    "address": "GaZb3DE2U3Jcjx7ddAVwobsBKnCaDoJWLbzTvJYhpump",
    "symbol": "ANSUM",
    "name": "the bleck bull",
    "market_cap_usd": 660763,
    "volume_24h_usd": 327297,
    "liquidity_usd": 72705,
    "logo_uri": "https://cdn.dexscreener.com/cms/images/ju5nj3-7sial9oFW?width=800&height=800&quality=95&format=auto",
    "dexscreener_url": "https://dexscreener.com/solana/GaZb3DE2U3Jcjx7ddAVwobsBKnCaDoJWLbzTvJYhpump",
    "decimals": 6
  },
  {
    "chain_slug": "solana",
    "chain_id": 501474,
    "address": "4SnKwnz6DyagftnFqdxsvWvehrcbEDhxmmXNQk2Jpump",
    "symbol": "Joby",
    "name": "Free Joby",
    "market_cap_usd": 3647601,
    "volume_24h_usd": 323982,
    "liquidity_usd": 170725,
    "logo_uri": "https://cdn.dexscreener.com/cms/images/qxjVI03LToRSxlUo?width=800&height=800&quality=95&format=auto",
    "dexscreener_url": "https://dexscreener.com/solana/4SnKwnz6DyagftnFqdxsvWvehrcbEDhxmmXNQk2Jpump",
    "decimals": 6
  },
  {
    "chain_slug": "solana",
    "chain_id": 501474,
    "address": "DkmmVCUaBAcYjecqMdX7NdNQFCfb6uh1yQq9HEP8pump",
    "symbol": "ANSEMIUS",
    "name": "Ansemius Bulleus",
    "market_cap_usd": 123473,
    "volume_24h_usd": 302044,
    "liquidity_usd": 30134,
    "logo_uri": "https://cdn.dexscreener.com/cms/images/S4y02SKkF1-xbFbH?width=800&height=800&quality=95&format=auto",
    "dexscreener_url": "https://dexscreener.com/solana/DkmmVCUaBAcYjecqMdX7NdNQFCfb6uh1yQq9HEP8pump",
    "decimals": 6
  },
  {
    "chain_slug": "solana",
    "chain_id": 501474,
    "address": "BWH6gtE5MSCS1GUoRpM5HrqQnV97oi8g8dDHAi41pump",
    "symbol": "Shadow",
    "name": "The bagworker",
    "market_cap_usd": 455677,
    "volume_24h_usd": 196854,
    "liquidity_usd": 52417,
    "logo_uri": "https://cdn.dexscreener.com/cms/images/NI4MVSypJdK4cmuk?width=800&height=800&quality=95&format=auto",
    "dexscreener_url": "https://dexscreener.com/solana/BWH6gtE5MSCS1GUoRpM5HrqQnV97oi8g8dDHAi41pump",
    "decimals": 6
  },
  {
    "chain_slug": "solana",
    "chain_id": 501474,
    "address": "8jayQDfRc3GYxftBJ2VAwjqmRBdYPC9KnjY15rc9pump",
    "symbol": "SAPIJIJU",
    "name": "The Frog",
    "market_cap_usd": 432216,
    "volume_24h_usd": 171610,
    "liquidity_usd": 59693,
    "logo_uri": "https://cdn.dexscreener.com/cms/images/QkPMZgcB1sVs47an?width=800&height=800&quality=95&format=auto",
    "dexscreener_url": "https://dexscreener.com/solana/8jayQDfRc3GYxftBJ2VAwjqmRBdYPC9KnjY15rc9pump",
    "decimals": 6
  },
  {
    "chain_slug": "solana",
    "chain_id": 501474,
    "address": "8XtRWb4uAAJFMP4QQhoYYCWR6XXb7ybcCdiqPwz9s5WS",
    "symbol": "ALON",
    "name": "alon",
    "market_cap_usd": 16136914,
    "volume_24h_usd": 167919,
    "liquidity_usd": 384823,
    "logo_uri": "https://cdn.dexscreener.com/cms/images/1a083c0e91b278817828e518ef7ab5513e75b79019cc9c569f033b8aa8fe1d41?width=800&height=800&quality=95&format=auto",
    "dexscreener_url": "https://dexscreener.com/solana/8XtRWb4uAAJFMP4QQhoYYCWR6XXb7ybcCdiqPwz9s5WS",
    "decimals": 6
  },
  {
    "chain_slug": "solana",
    "chain_id": 501474,
    "address": "7thY5PzYdH311NXYE6mecBjUs7wcosk1bWw2qfH4pump",
    "symbol": "Sapijiju",
    "name": "Sapijiju",
    "market_cap_usd": 157311,
    "volume_24h_usd": 150045,
    "liquidity_usd": 39849,
    "logo_uri": "https://cdn.dexscreener.com/cms/images/629c44848d2617de49d577d3d09f73571cc34871765535bea0d6c6f45c37058d?width=800&height=800&quality=95&format=auto",
    "dexscreener_url": "https://dexscreener.com/solana/7thY5PzYdH311NXYE6mecBjUs7wcosk1bWw2qfH4pump",
    "decimals": 6
  },
  {
    "chain_slug": "solana",
    "chain_id": 501474,
    "address": "6UGNg119LV6YjSCQ5K6Z6jsLLLetpMJ1vPdhiU8qpump",
    "symbol": "CURB",
    "name": "The Solana Bull",
    "market_cap_usd": 414748,
    "volume_24h_usd": 99096,
    "liquidity_usd": 36855,
    "logo_uri": "https://cdn.dexscreener.com/cms/images/1IKvGiUjj4X7fbiA?width=800&height=800&quality=95&format=auto",
    "dexscreener_url": "https://dexscreener.com/solana/6UGNg119LV6YjSCQ5K6Z6jsLLLetpMJ1vPdhiU8qpump",
    "decimals": 6
  },
  {
    "chain_slug": "solana",
    "chain_id": 501474,
    "address": "J9fVUSrsGYpuyXggAFJpf8WGkVsjqjCpBzyBxh6spump",
    "symbol": "DONALD",
    "name": "The American Bull",
    "market_cap_usd": 17707,
    "volume_24h_usd": 11492,
    "liquidity_usd": 8886,
    "logo_uri": "https://cdn.dexscreener.com/cms/images/bFm1rtwINLlcpb53?width=800&height=800&quality=95&format=auto",
    "dexscreener_url": "https://dexscreener.com/solana/J9fVUSrsGYpuyXggAFJpf8WGkVsjqjCpBzyBxh6spump",
    "decimals": 6
  },
  {
    "chain_slug": "solana",
    "chain_id": 501474,
    "address": "5asSNpLpxzZpkbqZkeuT3tCPPqWtZBQivbbrQHMcpump",
    "symbol": "KIRB",
    "name": "Help Alex's Mom",
    "market_cap_usd": 8533,
    "volume_24h_usd": 6247,
    "liquidity_usd": 8346,
    "logo_uri": "https://cdn.dexscreener.com/cms/images/_deDYE0ZdTxkeDIq?width=800&height=800&quality=95&format=auto",
    "dexscreener_url": "https://dexscreener.com/solana/5asSNpLpxzZpkbqZkeuT3tCPPqWtZBQivbbrQHMcpump",
    "decimals": 6
  },
  {
    "chain_slug": "solana",
    "chain_id": 501474,
    "address": "AVVLwZcNnts8JffDiEZxLNXGk9nLAzRr6hf9KDWapump",
    "symbol": "SAYLOR",
    "name": "The Orange Bull",
    "market_cap_usd": 18960,
    "volume_24h_usd": 5418,
    "liquidity_usd": 8926,
    "logo_uri": "https://cdn.dexscreener.com/cms/images/i8Dq49rkjOO9ChZW?width=800&height=800&quality=95&format=auto",
    "dexscreener_url": "https://dexscreener.com/solana/AVVLwZcNnts8JffDiEZxLNXGk9nLAzRr6hf9KDWapump",
    "decimals": 6
  },
  {
    "chain_slug": "solana",
    "chain_id": 501474,
    "address": "GgRYByJSNdRJo26LHeudCEPhwK6aVriktipYomHDpump",
    "symbol": "PUMPLON",
    "name": "PUMPLON MUSK",
    "market_cap_usd": 3266,
    "volume_24h_usd": 3353,
    "liquidity_usd": 4603,
    "logo_uri": "https://cdn.dexscreener.com/cms/images/jNT8BVUOU5mBqMx3?width=800&height=800&quality=95&format=auto",
    "dexscreener_url": "https://dexscreener.com/solana/GgRYByJSNdRJo26LHeudCEPhwK6aVriktipYomHDpump",
    "decimals": 6
  },
  {
    "chain_slug": "solana",
    "chain_id": 501474,
    "address": "6uYAQyXYMQ5sTNPRZmYSVMGTAzgkTrK5mGtHpPYCpump",
    "symbol": "Vaaland",
    "name": "Viking Haaland",
    "market_cap_usd": 4440,
    "volume_24h_usd": 789,
    "liquidity_usd": 6008,
    "logo_uri": "https://cdn.dexscreener.com/cms/images/l-i3OBGTYEr4STdP?width=800&height=800&quality=95&format=auto",
    "dexscreener_url": "https://dexscreener.com/solana/6uYAQyXYMQ5sTNPRZmYSVMGTAzgkTrK5mGtHpPYCpump",
    "decimals": 6
  },
  {
    "chain_slug": "solana",
    "chain_id": 501474,
    "address": "22oesKQuMBmxUTWfeFDjNnYS19VujFcBmi4EL8gWpump",
    "symbol": "GCAT",
    "name": "Graffiti Cat",
    "market_cap_usd": 2976,
    "volume_24h_usd": 114,
    "liquidity_usd": 5177,
    "logo_uri": "https://cdn.dexscreener.com/cms/images/2VaQJRCF_hS8kfSn?width=800&height=800&quality=95&format=auto",
    "dexscreener_url": "https://dexscreener.com/solana/22oesKQuMBmxUTWfeFDjNnYS19VujFcBmi4EL8gWpump",
    "decimals": 6
  }
]