[
  {
    "chain_slug": "solana",
    "chain_id": 501474,
    "address": "So11111111111111111111111111111111111111112",
    "symbol": "SOL",
    "name": "Wrapped SOL",
    "market_cap_usd": 46052752640,
    "volume_24h_usd": 112791518,
    "liquidity_usd": 23347414,
    "logo_uri": "https://cdn.dexscreener.com/cms/images/fcfb87378d3198fe753ca08ba51a5552a84f34cf48cd09d83971aa195bdf00d2?width=800&height=800&quality=95&format=auto",
    "pair_created_at_ms": 1669602308000,
    "dexscreener_url": "https://dexscreener.com/solana/So11111111111111111111111111111111111111112",
    "decimals": 9
  },
  {
    "chain_slug": "base",
    "chain_id": 8453,
    "address": "0xcbb7c0000ab88b473b1f5afd9ef808440eed33bf",
    "symbol": "cbBTC",
    "name": "Coinbase Wrapped BTC",
    "market_cap_usd": 2648798351,
    "volume_24h_usd": 53691244,
    "liquidity_usd": 10148785,
    "logo_uri": "https://cdn.dexscreener.com/cms/images/07ce833f9dde758de45cb2476e630226f9b58418bb20e0f7ce3885c5d0d80b1b?width=800&height=800&quality=95&format=auto",
    "pair_created_at_ms": 1726084175000,
    "dexscreener_url": "https://dexscreener.com/base/0xcbb7c0000ab88b473b1f5afd9ef808440eed33bf",
    "decimals": 8
  },
  {
    "chain_slug": "base",
    "chain_id": 8453,
    "address": "0x4200000000000000000000000000000000000006",
    "symbol": "WETH",
    "name": "Wrapped Ether",
    "market_cap_usd": 485617223,
    "volume_24h_usd": 18463641,
    "liquidity_usd": 3859072,
    "logo_uri": "https://cdn.dexscreener.com/cms/images/e7ad3f643e8706e541538413f2afad46f18cafb430606caae3c70c0f7425c16e?width=800&height=800&quality=95&format=auto",
    "pair_created_at_ms": 1697608465000,
    "dexscreener_url": "https://dexscreener.com/base/0x4200000000000000000000000000000000000006",
    "decimals": 18
  },
  {
    "chain_slug": "solana",
    "chain_id": 501474,
    "address": "2JcqSpiK8e8F8dkqaQtkyb9umoJdzGz3qemnMKXApump",
    "symbol": "PEVOLUTION",
    "name": "Pevolution",
    "market_cap_usd": 982506,
    "volume_24h_usd": 13930208,
    "liquidity_usd": 10933,
    "logo_uri": "https://cdn.dexscreener.com/cms/images/KuCWbjR65X0JZL6V?width=800&height=800&quality=95&format=auto",
    "dexscreener_url": "https://dexscreener.com/solana/2JcqSpiK8e8F8dkqaQtkyb9umoJdzGz3qemnMKXApump",
    "decimals": 6
  },
  {
    "chain_slug": "solana",
    "chain_id": 501474,
    "address": "EmcxFTNVDqyLHp11NvwvLZ4D7LKGbG9i7B8RF7dwpump",
    "symbol": "ZERO",
    "name": "c0mpute",
    "market_cap_usd": 2873417686,
    "volume_24h_usd": 9029164,
    "liquidity_usd": 401942,
    "logo_uri": "https://cdn.dexscreener.com/cms/images/PhSpON2tr_xLYYxc?width=800&height=800&quality=95&format=auto",
    "dexscreener_url": "https://dexscreener.com/solana/EmcxFTNVDqyLHp11NvwvLZ4D7LKGbG9i7B8RF7dwpump",
    "decimals": 6
  },
  {
    "chain_slug": "base",
    "chain_id": 8453,
    "address": "0x940181a94a35a4569e4529a3cdfb74e38fd98631",
    "symbol": "AERO",
    "name": "Aerodrome",
    "market_cap_usd": 526658295,
    "volume_24h_usd": 6738185,
    "liquidity_usd": 27653352,
    "logo_uri": "https://cdn.dexscreener.com/cms/images/f950c4e0a9ded4f6b5c811cf33570a65c6f7ea8630d937cd69065269e9dc3a03?width=800&height=800&quality=95&format=auto",
    "pair_created_at_ms": 1694127045000,
    "dexscreener_url": "https://dexscreener.com/base/0x940181a94a35a4569e4529a3cdfb74e38fd98631",
    "decimals": 18
  },
  {
    "chain_slug": "solana",
    "chain_id": 501474,
    "address": "489fWM9Ur6m3N6KBHUc3BegesUSH6Z3J5UH1USZnpump",
    "symbol": "Harvest Hank",
    "name": "Harvest Hank",
    "market_cap_usd": 704056,
    "volume_24h_usd": 4918120,
    "liquidity_usd": 15112,
    "logo_uri": "https://cdn.dexscreener.com/cms/images/L8keO9aazPTBEGIA?width=800&height=800&quality=95&format=auto",
    "dexscreener_url": "https://dexscreener.com/solana/489fWM9Ur6m3N6KBHUc3BegesUSH6Z3J5UH1USZnpump",
    "decimals": 6
  },
  {
    "chain_slug": "solana",
    "chain_id": 501474,
    "address": "Es9vMFrzaCERmJfrF4H2FYD4KCoNkY11McCe8BenwNYB",
    "symbol": "USDT",
    "name": "USDT",
    "market_cap_usd": 186471454928,
    "volume_24h_usd": 4647417,
    "liquidity_usd": 360036244,
    "logo_uri": "https://cdn.dexscreener.com/cms/images/ad986e3ebe668b0c5ed2ecec0f6bcdc2f4cda3ad8a424a252d33f730c75364a7?width=800&height=800&quality=95&format=auto",
    "pair_created_at_ms": 1669602314000,
    "dexscreener_url": "https://dexscreener.com/solana/Es9vMFrzaCERmJfrF4H2FYD4KCoNkY11McCe8BenwNYB",
    "decimals": 6
  },
  {
    "chain_slug": "solana",
    "chain_id": 501474,
    "address": "5UUH9RTDiSpq6HKS6bp4NdU9PNJpXRXuiw6ShBTBhgH2",
    "symbol": "TROLL",
    "name": "TROLL",
    "market_cap_usd": 74306188,
    "volume_24h_usd": 4470265,
    "liquidity_usd": 3092949,
    "logo_uri": "https://cdn.dexscreener.com/cms/images/tLIgpz8Fa_O1THOX?width=800&height=800&quality=95&format=auto",
    "pair_created_at_ms": 1745166438000,
    "dexscreener_url": "https://dexscreener.com/solana/5UUH9RTDiSpq6HKS6bp4NdU9PNJpXRXuiw6ShBTBhgH2",
    "decimals": 6
  },
  {
    "chain_slug": "solana",
    "chain_id": 501474,
    "address": "Tqj8yFmagrg7oorpQkVGYR52r96RFTamvWfth9bpump",
    "symbol": "KINS",
    "name": "Kintara",
    "market_cap_usd": 15701375,
    "volume_24h_usd": 3404230,
    "liquidity_usd": 422885,
    "logo_uri": "https://cdn.dexscreener.com/cms/images/eDgwf9dPmPRrNv8_?width=800&height=800&quality=95&format=auto",
    "pair_created_at_ms": 1779472043000,
    "dexscreener_url": "https://dexscreener.com/solana/Tqj8yFmagrg7oorpQkVGYR52r96RFTamvWfth9bpump",
    "decimals": 6
  },
  {
    "chain_slug": "solana",
    "chain_id": 501474,
    "address": "CARDSccUMFKoPRZxt5vt3ksUbxEFEcnZ3H2pd3dKxYjp",
    "symbol": "CARDS",
    "name": "Collector Crypt",
    "market_cap_usd": 82981116,
    "volume_24h_usd": 3318726,
    "liquidity_usd": 3843918,
    "logo_uri": "https://cdn.dexscreener.com/cms/images/3277f5f414a940e7d009f9cbc9147c6ab25eae6a6cda10e682319f7b6394e328?width=800&height=800&quality=95&format=auto",
    "pair_created_at_ms": 1756493686000,
    "dexscreener_url": "https://dexscreener.com/solana/CARDSccUMFKoPRZxt5vt3ksUbxEFEcnZ3H2pd3dKxYjp",
    "decimals": 6
  },
  {
    "chain_slug": "base",
    "chain_id": 8453,
    "address": "0x0b3e328455c4059eeb9e3f84b5543f74e24e7e1b",
    "symbol": "VIRTUAL",
    "name": "Virtual Protocol",
    "market_cap_usd": 400580089,
    "volume_24h_usd": 3243276,
    "liquidity_usd": 499257,
    "logo_uri": "https://cdn.dexscreener.com/cms/images/461f4a6b70979b82b7141adc522389c67043535a082d65accebf49013c798386?width=800&height=800&quality=95&format=auto",
    "pair_created_at_ms": 1710514799000,
    "dexscreener_url": "https://dexscreener.com/base/0x0b3e328455c4059eeb9e3f84b5543f74e24e7e1b",
    "decimals": 18
  },
  {
    "chain_slug": "base",
    "chain_id": 8453,
    "address": "0xbf927b841994731c573bdf09ceb0c6b0aa887cdd",
    "symbol": "VELVET",
    "name": "Velvet",
    "market_cap_usd": 207121020,
    "volume_24h_usd": 2938918,
    "liquidity_usd": 3439959,
    "logo_uri": "https://cdn.dexscreener.com/cms/images/922f6888648f06e8a6e228aef05660cc68814596d9921d33efea723cf16b77ff?width=800&height=800&quality=95&format=auto",
    "pair_created_at_ms": 1757351299000,
    "dexscreener_url": "https://dexscreener.com/base/0xbf927b841994731c573bdf09ceb0c6b0aa887cdd",
    "decimals": 18
  },
  {
    "chain_slug": "base",
    "chain_id": 8453,
    "address": "0x311935cd80b76769bf2ecc9d8ab7635b2139cf82",
    "symbol": "SOL",
    "name": "Solana",
    "market_cap_usd": 12969386,
    "volume_24h_usd": 2599178,
    "liquidity_usd": 242984,
    "logo_uri": "https://cdn.dexscreener.com/cms/images/e06bde6f35af4295de2c1b039f242b464012689ad6fc669ee977a9148b2eb936?width=800&height=800&quality=95&format=auto",
    "pair_created_at_ms": 1764722545000,
    "dexscreener_url": "https://dexscreener.com/base/0x311935cd80b76769bf2ecc9d8ab7635b2139cf82",
    "decimals": 9
  },
  {
    "chain_slug": "solana",
    "chain_id": 501474,
    "address": "37Bk2fdJ4gNGXrYTjMdriaZUbBbhmoQGeQjHyih3pump",
    "symbol": "QAI",
    "name": "Qai",
    "market_cap_usd": 1670929,
    "volume_24h_usd": 2340862,
    "liquidity_usd": 100386,
    "logo_uri": "https://cdn.dexscreener.com/cms/images/of2Lb0gEDUM9Of4W?width=800&height=800&quality=95&format=auto",
    "dexscreener_url": "https://dexscreener.com/solana/37Bk2fdJ4gNGXrYTjMdriaZUbBbhmoQGeQjHyih3pump",
    "decimals": 6
  },
  {
    "chain_slug": "solana",
    "chain_id": 501474,
    "address": "BcHEaaTCvycPwwsJ9yQTXdHP9X2gCLkznDbZ8VySpump",
    "symbol": "Jotchua",
    "name": "Jotchua",
    "market_cap_usd": 7202603,
    "volume_24h_usd": 2279455,
    "liquidity_usd": 353994,
    "logo_uri": "https://cdn.dexscreener.com/cms/images/NPs1Oxrt4x4Il_WB?width=800&height=800&quality=95&format=auto",
    "pair_created_at_ms": 1780809325000,
    "dexscreener_url": "https://dexscreener.com/solana/BcHEaaTCvycPwwsJ9yQTXdHP9X2gCLkznDbZ8VySpump",
    "decimals": 6
  },
  {
    "chain_slug": "solana",
    "chain_id": 501474,
    "address": "BPxxfRCXkUVhig4HS1Lh7kZqV6SPJhzfEk4x6fVBjPCy",
    "symbol": "BP",
    "name": "Backpack",
    "market_cap_usd": 175593203,
    "volume_24h_usd": 1889111,
    "liquidity_usd": 2307308,
    "logo_uri": "https://cdn.dexscreener.com/cms/images/lRgHuo2WCyUOAcFJ?width=800&height=800&quality=95&format=auto",
    "dexscreener_url": "https://dexscreener.com/solana/BPxxfRCXkUVhig4HS1Lh7kZqV6SPJhzfEk4x6fVBjPCy",
    "decimals": 9
  },
  {
    "chain_slug": "solana",
    "chain_id": 501474,
    "address": "8wxkvAfEns76yBzu4MnbV7VnXWjg3iDPA9uwAQ6cpump",
    "symbol": "SOLANGELES",
    "name": "SolAngeles",
    "market_cap_usd": 2637958,
    "volume_24h_usd": 1870911,
    "liquidity_usd": 127747,
    "logo_uri": "https://cdn.dexscreener.com/cms/images/pi8udfIf51qcX95D?width=800&height=800&quality=95&format=auto",
    "dexscreener_url": "https://dexscreener.com/solana/8wxkvAfEns76yBzu4MnbV7VnXWjg3iDPA9uwAQ6cpump",
    "decimals": 6
  },
  {
    "chain_slug": "base",
    "chain_id": 8453,
    "address": "0x9126236476efba9ad8ab77855c60eb5bf37586eb",
    "symbol": "CHECK",
    "name": "Checkmate",
    "market_cap_usd": 10539041,
    "volume_24h_usd": 1814083,
    "liquidity_usd": 150234,
    "logo_uri": "https://cdn.dexscreener.com/cms/images/5f5e4c0464a938976ae6ff90eb74606de25b27f9102ba15305353bb9a2cc950c?width=800&height=800&quality=95&format=auto",
    "pair_created_at_ms": 1762991043000,
    "dexscreener_url": "https://dexscreener.com/base/0x9126236476efba9ad8ab77855c60eb5bf37586eb",
    "decimals": 18
  },
  {
    "chain_slug": "solana",
    "chain_id": 501474,
    "address": "yMJPZbnhoHib3ib8n8PfiVcp9yauk1vnaGKLx7epump",
    "symbol": "FARM",
    "name": "FarmTown",
    "market_cap_usd": 1656263,
    "volume_24h_usd": 1682405,
    "liquidity_usd": 98582,
    "logo_uri": "https://cdn.dexscreener.com/cms/images/GR1puZAnLD0GxDJi?width=800&height=800&quality=95&format=auto",
    "dexscreener_url": "https://dexscreener.com/solana/yMJPZbnhoHib3ib8n8PfiVcp9yauk1vnaGKLx7epump",
    "decimals": 6
  },
  {
    "chain_slug": "solana",
    "chain_id": 501474,
    "address": "C1mg2ddme7Hpwjmxngr1AfrwRSmLqL1CVHPzUmapEory",
    "symbol": "FLKR",
    "name": "FalkorDB",
    "market_cap_usd": 2148448,
    "volume_24h_usd": 1615523,
    "liquidity_usd": 157018,
    "logo_uri": "https://cdn.dexscreener.com/cms/images/pa8r3iDFUB0nMjP5?width=800&height=800&quality=95&format=auto",
    "dexscreener_url": "https://dexscreener.com/solana/C1mg2ddme7Hpwjmxngr1AfrwRSmLqL1CVHPzUmapEory",
    "decimals": 6
  },
  {
    "chain_slug": "base",
    "chain_id": 8453,
    "address": "0x9b5e262cf9bb04869ab40b19af91d2dc85761722",
    "symbol": "NOCK",
    "name": "Nock",
    "market_cap_usd": 83392103,
    "volume_24h_usd": 1610405,
    "liquidity_usd": 1248405,
    "logo_uri": "https://cdn.dexscreener.com/cms/images/e91dae43a83597be54fae8861b6c64ce73b05e43388357e1e9fd68ee1d840938?width=800&height=800&quality=95&format=auto",
    "pair_created_at_ms": 1766440359000,
    "dexscreener_url": "https://dexscreener.com/base/0x9b5e262cf9bb04869ab40b19af91d2dc85761722",
    "decimals": 16
  },
  {
    "chain_slug": "base",
    "chain_id": 8453,
    "address": "0x16ee7ecac70d1028e7712751e2ee6ba808a7dd92",
    "symbol": "FUN",
    "name": "Sport.fun",
    "market_cap_usd": 4905814,
    "volume_24h_usd": 1569620,
    "liquidity_usd": 443961,
    "logo_uri": "https://cdn.dexscreener.com/cms/images/ede0e39416d2b469a7f60391f9a35c12b5d89f7f9b010ecf05770533032ce421?width=800&height=800&quality=95&format=auto",
    "pair_created_at_ms": 1768473557000,
    "dexscreener_url": "https://dexscreener.com/base/0x16ee7ecac70d1028e7712751e2ee6ba808a7dd92",
    "decimals": 18
  },
  {
    "chain_slug": "solana",
    "chain_id": 501474,
    "address": "E8UXwqhNiiMwVRRV4F81rUBUYXNUd4bA78ZxpQxZpump",
    "symbol": "JAMESON",
    "name": "Justice For Jameson The Doodle",
    "market_cap_usd": 851587,
    "volume_24h_usd": 1394431,
    "liquidity_usd": 52259,
    "logo_uri": "https://cdn.dexscreener.com/cms/images/-jfRxRets9r54R-d?width=800&height=800&quality=95&format=auto",
    "dexscreener_url": "https://dexscreener.com/solana/E8UXwqhNiiMwVRRV4F81rUBUYXNUd4bA78ZxpQxZpump",
    "decimals": 6
  },
  {
    "chain_slug": "solana",
    "chain_id": 501474,
    "address": "9G4Z9wkL851RZfMFHQETQ6v5GSNqkUTXC5oBtUXcXw1W",
    "symbol": "bullieve",
    "name": "bullieve",
    "market_cap_usd": 241368,
    "volume_24h_usd": 1311145,
    "liquidity_usd": 28044,
    "logo_uri": "https://cdn.dexscreener.com/cms/images/gduHNGOJ5iajF-7u?width=800&height=800&quality=95&format=auto",
    "dexscreener_url": "https://dexscreener.com/solana/9G4Z9wkL851RZfMFHQETQ6v5GSNqkUTXC5oBtUXcXw1W",
    "decimals": 6
  },
  {
    "chain_slug": "base",
    "chain_id": 8453,
    "address": "0x11030f79109269d796fd0fb956d6244e502757f7",
    "symbol": "CTR",
    "name": "CTR",
    "market_cap_usd": 13919847,
    "volume_24h_usd": 1203408,
    "liquidity_usd": 558875,
    "logo_uri": "https://cdn.dexscreener.com/cms/images/xsdi0rIB9BatQGAJ?width=800&height=800&quality=95&format=auto",
    "pair_created_at_ms": 1779784861000,
    "dexscreener_url": "https://dexscreener.com/base/0x11030f79109269d796fd0fb956d6244e502757f7",
    "decimals": 18
  },
  {
    "chain_slug": "base",
    "chain_id": 8453,
    "address": "0xacfe6019ed1a7dc6f7b508c02d1b04ec88cc21bf",
    "symbol": "VVV",
    "name": "Venice Token",
    "market_cap_usd": 676577062,
    "volume_24h_usd": 1055265,
    "liquidity_usd": 2898463,
    "logo_uri": "https://cdn.dexscreener.com/cms/images/a581d4cf10079a278196c97485dda06cf4fb77d539a94f8d986be6d1f2445ddc?width=800&height=800&quality=95&format=auto",
    "pair_created_at_ms": 1737996283000,
    "dexscreener_url": "https://dexscreener.com/base/0xacfe6019ed1a7dc6f7b508c02d1b04ec88cc21bf",
    "decimals": 18
  },
  {
    "chain_slug": "base",
    "chain_id": 8453,
    "address": "0x6985884c4392d348587b19cb9eaaf157f13271cd",
    "symbol": "ZRO",
    "name": "LayerZero",
    "market_cap_usd": 227187456,
    "volume_24h_usd": 1022308,
    "liquidity_usd": 412238,
    "logo_uri": "https://cdn.dexscreener.com/cms/images/dCYbpM8trK0djNDB?width=800&height=800&quality=95&format=auto",
    "pair_created_at_ms": 1718802125000,
    "dexscreener_url": "https://dexscreener.com/base/0x6985884c4392d348587b19cb9eaaf157f13271cd",
    "decimals": 18
  },
  {
    "chain_slug": "solana",
    "chain_id": 501474,
    "address": "ACpzkGJV3DDU8HXy8yjab7RL9qNmDGym2GwLkzNppump",
    "symbol": "SON",
    "name": "Are Ya Winning, Son?",
    "market_cap_usd": 1557682,
    "volume_24h_usd": 848292,
    "liquidity_usd": 112402,
    "logo_uri": "https://cdn.dexscreener.com/cms/images/LWXfbJbEnJLnq6f5?width=800&height=800&quality=95&format=auto",
    "dexscreener_url": "https://dexscreener.com/solana/ACpzkGJV3DDU8HXy8yjab7RL9qNmDGym2GwLkzNppump",
    "decimals": 6
  },
  {
    "chain_slug": "solana",
    "chain_id": 501474,
    "address": "EpVHyKK8oxcLmp2C2NhAos1oDxgBNriw3wSLSozYpump",
    "symbol": "GTAVI",
    "name": "Grand Theft Auto VI",
    "market_cap_usd": 1096885,
    "volume_24h_usd": 825162,
    "liquidity_usd": 85812,
    "logo_uri": "https://cdn.dexscreener.com/cms/images/3LJ7K2S-7KAQUmVT?width=800&height=800&quality=95&format=auto",
    "dexscreener_url": "https://dexscreener.com/solana/EpVHyKK8oxcLmp2C2NhAos1oDxgBNriw3wSLSozYpump",
    "decimals": 6
  },
  {
    "chain_slug": "solana",
    "chain_id": 501474,
    "address": "AvxFBjWydMYWD7C8pHzSkGxNYAFWr7aNBbAKm84bpump",
    "symbol": "Merlin",
    "name": "The Patriotic Duck",
    "market_cap_usd": 1075869,
    "volume_24h_usd": 809312,
    "liquidity_usd": 96284,
    "logo_uri": "https://cdn.dexscreener.com/cms/images/bN7USSvr2ptR7UW5?width=800&height=800&quality=95&format=auto",
    "dexscreener_url": "https://dexscreener.com/solana/AvxFBjWydMYWD7C8pHzSkGxNYAFWr7aNBbAKm84bpump",
    "decimals": 6
  },
  {
    "chain_slug": "solana",
    "chain_id": 501474,
    "address": "hYfm7JwKcpEfdh41c2bwHT5AsJF8At3rPuvu8avpump",
    "symbol": "PROVE",
    "name": "PROVE IT",
    "market_cap_usd": 54460,
    "volume_24h_usd": 420185,
    "liquidity_usd": 23465,
    "logo_uri": "https://cdn.dexscreener.com/cms/images/lf1XnnCjJmfDCsXr?width=800&height=800&quality=95&format=auto",
    "dexscreener_url": "https://dexscreener.com/solana/hYfm7JwKcpEfdh41c2bwHT5AsJF8At3rPuvu8avpump",
    "decimals": 6
  },
  {
    "chain_slug": "solana",
    "chain_id": 501474,
    "address": "5M5yNMXUpVAgYZN9mV1jHPn61EaHPaYE5iy3ZhFKJJed",
    "symbol": "PEACE",
    "name": "Peace Token",
    "market_cap_usd": 5336559,
    "volume_24h_usd": 15487,
    "liquidity_usd": 257052,
    "logo_uri": "https://cdn.dexscreener.com/cms/images/80mp199q85VsZUc-?width=800&height=800&quality=95&format=auto",
    "dexscreener_url": "https://dexscreener.com/solana/5M5yNMXUpVAgYZN9mV1jHPn61EaHPaYE5iy3ZhFKJJed",
    "decimals": 6
  },
  {
    "chain_slug": "solana",
    "chain_id": 501474,
    "address": "EkHFmmqJMz95jaeNGj9onEAtzWdLtjqmRNsqov28BAGS",
    "symbol": "1B",
    "name": "Speedrun to 1b",
    "market_cap_usd": 11146780,
    "volume_24h_usd": 2622,
    "liquidity_usd": 46988,
    "logo_uri": "https://cdn.dexscreener.com/cms/images/PNtfA8-hg6JdxH0z?width=800&height=800&quality=95&format=auto",
    "dexscreener_url": "https://dexscreener.com/solana/EkHFmmqJMz95jaeNGj9onEAtzWdLtjqmRNsqov28BAGS",
    "decimals": 9
  }
]