[
  {
    "chain_slug": "solana",
    "address": "7v6sk63y8rr1mvcn5mynp61wgfhy4eeqg5guask9pump",
    "symbol": "HBULL",
    "direction": "pump",
    "price_change_h1_pct": 23.145,
    "timestamp": 1784038965.353331
  },
  {
    "chain_slug": "solana",
    "address": "9odndfic7rw42vzcmszactkmwe9kgeqnzwxdglskpump",
    "symbol": "brain",
    "direction": "pump",
    "price_change_h1_pct": -3.096,
    "timestamp": 1784035369.0003703
  },
  {
    "chain_slug": "solana",
    "address": "f4gpafr6vrxu3y887f3xwkxrgybcvjznk63m72f6pump",
    "symbol": "TrumpCoin",
    "direction": "pump",
    "price_change_h1_pct": 34.986,
    "timestamp": 1784027400.826206
  }
]